changes.txt
readme.txt
setup.py
src/ore/__init__.py
src/ore.yui.egg-info/PKG-INFO
src/ore.yui.egg-info/SOURCES.txt
src/ore.yui.egg-info/dependency_links.txt
src/ore.yui.egg-info/namespace_packages.txt
src/ore.yui.egg-info/not-zip-safe
src/ore.yui.egg-info/requires.txt
src/ore.yui.egg-info/top_level.txt
src/ore/yui/README.txt
src/ore/yui/__init__.py
src/ore/yui/configure.zcml
src/ore/yui/css.py
src/ore/yui/interfaces.py
src/ore/yui/js.py
src/ore/yui/reslib.zcml
src/ore/yui/viewlet.zcml