Metadata-Version: 1.0
Name: ore.yui
Version: 0.5.3
Summary: Zope3 Package of the YUI library
Home-page: http://pypi.python.org/pypi/ore.yui
Author: Kapil Thangavelu
Author-email: kapil.foss@gmail.com
License: UNKNOWN
Platform: UNKNOWN
Classifier: Programming Language :: Python
Classifier: Environment :: Web Environment
Classifier: Topic :: Internet :: WWW/HTTP :: WSGI :: Application
Classifier: Framework :: Zope3
